{
  "stac_version": "1.0.0",
  "stac_extensions": [],
  "type": "Feature",
  "id": "MOZ_set_lightscore_2020",
  "bbox": [
    30.22293485900000,
    -27.41963907800000,
    40.84626827700000,
    -10.16297227400000
  ],
  "geometry": {
    "type": "Polygon",
    "coordinates": [
      [
        [
          30.22293485900000,
          -27.41963907800000
        ],
        [
          40.84626827700000,
          -27.41963907800000
        ],
        [
          40.84626827700000,
          -10.16297227400000
        ],
        [
          30.22293485900000,
          -10.16297227400000
        ],
        [
          30.22293485900000,
          -27.41963907800000
        ]
      ]
    ]
  },
  "properties": {
    "title": "Settlement lightscores for MOZ, 2020",
    "description": "Settlement lightscores in 2020 for Mozambique",
    "datetime": null,
    "start_datetime": "2020-01-01T00:00:00.000Z",
    "end_datetime": "2020-12-31T23:59:59.999Z"
  },
  "collection": "MOZ-MOZ-set_lightscore-collection",
  "links": [
    {
      "rel": "collection",
      "href": "./collection.json",
      "type": "application/json",
      "title": "MOZ-MOZ set_lightscore Collection"
    },
    {
      "rel": "root",
      "href": "././././catalog.json",
      "type": "application/json",
      "title": "HREA Catalog"
    },
    {
      "rel": "parent",
      "href": "./collection.json",
      "type": "application/json",
      "title": "MOZ-MOZ set_lightscore Collection"
    }
  ],
  "assets": {
    "set_lightscore": {
      "href": "https://globalnightlight.s3.amazonaws.com/HREAv1.1_COGs/MOZ/MOZ/set_lightscore/MOZ_set_lightscore_2020.tif",
      "type": "image/tiff; application=geotiff; profile=cloud-optimized",
      "title": "Settlement lightscores for MOZ, 2020",
      "roles": [
        "data"
      ]
    }
  }
}
